README.md
setup.py
tagy.py
tagy.egg-info/PKG-INFO
tagy.egg-info/SOURCES.txt
tagy.egg-info/dependency_links.txt
tagy.egg-info/requires.txt
tagy.egg-info/top_level.txt