Metadata-Version: 1.1
Name: tagy
Version: 0.1.7
Summary: Static site generator
Home-page: https://github.com/melnikov-ivan/tagy
Author: Ivan Melnikov
Author-email: melnikov.ivan@gmail.com
License: MIT
Keywords: Jinja2 fully customizable static site generator
Platform: UNKNOWN
Classifier: Development Status :: 5 - Production/Stable
Classifier: Intended Audience :: Developers
Classifier: Topic :: Software Development :: Build Tools
Classifier: License :: OSI Approved :: MIT License
Classifier: Programming Language :: Python :: 2.7
